pyreportxl/__init__.py
pyreportxl/cli.py
pyreportxl/pyreportxl.py
pyreportxl-0.1.0.dist-info/DESCRIPTION.rst
pyreportxl-0.1.0.dist-info/METADATA
pyreportxl-0.1.0.dist-info/RECORD
pyreportxl-0.1.0.dist-info/WHEEL
pyreportxl-0.1.0.dist-info/entry_points.txt
pyreportxl-0.1.0.dist-info/metadata.json
pyreportxl-0.1.0.dist-info/top_level.txt
tests/__init__.py
tests/test_pyreportxl.py
