Metadata-Version: 2.0
Name: pyreportxl
Version: 0.1.0
Summary: An Excel reporting framework for python.
Home-page: https://github.com/ChrisPappalardo/pyreportxl
Author: Chris Pappalardo
Author-email: cpappala@yahoo.com
License: MIT license
Keywords: pyreportxl
Platform: UNKNOWN
Classifier: Development Status :: 2 - Pre-Alpha
Classifier: Intended Audience :: Developers
Classifier: License :: OSI Approved :: MIT License
Classifier: Natural Language :: English
Classifier: Programming Language :: Python :: 2
Classifier: Programming Language :: Python :: 2.7
Classifier: Programming Language :: Python :: 3
Classifier: Programming Language :: Python :: 3.4
Requires-Dist: SQLAlchemy
Requires-Dist: click
Requires-Dist: pyexcel
Requires-Dist: pyexcel-xlsx
